{
  "_class": "shapeGroup",
  "clippingMaskMode": 0,
  "do_objectID": "0A218E14-D93B-4242-9382-D02F7CDF5C6E",
  "exportOptions": {
    "_class": "exportOptions",
    "do_objectID": "12E6CFB0-F650-4402-9801-8F18C07FBA42",
    "exportFormats": [
    ],
    "includedLayerIds": [
    ],
    "layerOptions": 0,
    "shouldTrim": false
  },
  "frame": {
    "_class": "rect",
    "constrainProportions": false,
    "do_objectID": "E0BA29B0-EAD6-4BFD-8614-CE63088BF0C7",
    "height": 75.32863035266065,
    "width": 58.6081732359758,
    "x": 0.5441253103459758,
    "y": 0.9607462509411562
  },
  "hasClickThrough": false,
  "hasClippingMask": true,
  "isFlippedHorizontal": false,
  "isFlippedVertical": false,
  "isLocked": false,
  "isVisible": true,
  "layerListExpandedType": 0,
  "layers": [
    {
      "class": "shapePath",
      "id": "B0EC7DB4-1F12-436F-8D2C-1B8C796A6919"
    }
  ],
  "name": "Clip 32",
  "nameIsFixed": false,
  "resizingConstraint": 63,
  "resizingType": 0,
  "rotation": 0,
  "shouldBreakMaskChain": false,
  "style": {
    "_class": "style",
    "do_objectID": "4DF6439C-1918-48AE-804A-4549CB37D111",
    "endDecorationType": 0,
    "miterLimit": 10,
    "startDecorationType": 0
  },
  "windingRule": 1
}