{
  "_class": "shapeGroup",
  "clippingMaskMode": 0,
  "do_objectID": "30892FB9-BDA9-4085-9E17-9D12A5D6207B",
  "exportOptions": {
    "_class": "exportOptions",
    "exportFormats": [
    ],
    "includedLayerIds": [
    ],
    "layerOptions": 0,
    "shouldTrim": false
  },
  "frame": {
    "_class": "rect",
    "constrainProportions": false,
    "height": 1.463578540322487,
    "width": 56.2677014660585,
    "x": 603.8597428416833,
    "y": 260.2047341675134
  },
  "hasClickThrough": false,
  "hasClippingMask": false,
  "isFlippedHorizontal": false,
  "isFlippedVertical": false,
  "isLocked": false,
  "isVisible": true,
  "layerListExpandedType": 0,
  "layers": [
    {
      "class": "shapePath",
      "id": "BF1501BE-B7C2-40BE-B34C-D4726629967F"
    }
  ],
  "name": "Stroke 8 Copy 13",
  "nameIsFixed": false,
  "resizingConstraint": 63,
  "resizingType": 0,
  "rotation": -33,
  "shouldBreakMaskChain": false,
  "style": {
    "_class": "style",
    "blur": {
      "_class": "blur",
      "center": "{0.5, 0.5}",
      "isEnabled": false,
      "motionAngle": 0,
      "radius": 4.32,
      "type": 0
    },
    "borders": [
      {
        "_class": "border",
        "color": {
          "_class": "color",
          "alpha": 1,
          "blue": 0.478,
          "green": 0.247,
          "red": 0.925
        },
        "fillType": 0,
        "isEnabled": true,
        "position": 0,
        "thickness": 0.5
      }
    ],
    "endDecorationType": 0,
    "miterLimit": 10,
    "startDecorationType": 0
  },
  "userInfo": {
    "com.animaapp.stc-sketch-plugin": {
      "kModelPropertiesKey": {
      }
    }
  },
  "windingRule": 1
}