{
  "_class": "shapeGroup",
  "clippingMaskMode": 0,
  "do_objectID": "520D5A87-97EA-44B6-8709-7BA385201EE6",
  "exportOptions": {
    "_class": "exportOptions",
    "exportFormats": [
    ],
    "includedLayerIds": [
    ],
    "layerOptions": 0,
    "shouldTrim": false
  },
  "frame": {
    "_class": "rect",
    "constrainProportions": false,
    "height": 3.75692307692308,
    "width": 3.667899247175598,
    "x": 166.0910503764122,
    "y": 34.97846153846154
  },
  "hasClickThrough": false,
  "hasClippingMask": false,
  "isFlippedHorizontal": false,
  "isFlippedVertical": false,
  "isLocked": false,
  "isVisible": true,
  "layerListExpandedType": 1,
  "layers": [
    {
      "class": "shapePath",
      "id": "61CAC8D1-2FEC-41D5-8A30-56F9BCCE24B8"
    },
    {
      "class": "shapePath",
      "id": "3AB91426-FC26-417F-99A6-FC349BAB34E4"
    },
    {
      "class": "shapePath",
      "id": "3DA293CE-3952-435A-AE41-41475A95CD6B"
    },
    {
      "class": "shapePath",
      "id": "AD7C7300-4427-4885-AFDD-7DA5790B9E86"
    }
  ],
  "name": "Shape",
  "nameIsFixed": false,
  "resizingConstraint": 63,
  "resizingType": 0,
  "rotation": 0,
  "shouldBreakMaskChain": false,
  "style": {
    "_class": "style",
    "blur": {
      "_class": "blur",
      "center": "{0.5, 0.5}",
      "isEnabled": false,
      "motionAngle": 0,
      "radius": 5,
      "type": 0
    },
    "endDecorationType": 0,
    "fills": [
      {
        "_class": "fill",
        "color": {
          "_class": "color",
          "alpha": 1,
          "blue": 1,
          "green": 1,
          "red": 1
        },
        "fillType": 0,
        "isEnabled": true,
        "noiseIndex": 0,
        "noiseIntensity": 0,
        "patternFillType": 1,
        "patternTileScale": 1
      }
    ],
    "miterLimit": 10,
    "startDecorationType": 0
  },
  "windingRule": 0
}