{
  "_class": "group",
  "do_objectID": "77D082AF-7AB1-47A4-9B44-8464C248CE40",
  "exportOptions": {
    "_class": "exportOptions",
    "exportFormats": [
    ],
    "includedLayerIds": [
    ],
    "layerOptions": 0,
    "shouldTrim": false
  },
  "frame": {
    "_class": "rect",
    "constrainProportions": false,
    "height": 24,
    "width": 184,
    "x": 207,
    "y": 2280
  },
  "hasClickThrough": false,
  "isFlippedHorizontal": false,
  "isFlippedVertical": false,
  "isLocked": false,
  "isVisible": true,
  "layerListExpandedType": 0,
  "layers": [
    {
      "class": "text",
      "id": "410326B0-B094-4382-87C0-91847C36AD91"
    },
    {
      "class": "shapeGroup",
      "id": "AF68995E-2FA6-4E08-B2EC-95BD88A8BA34"
    },
    {
      "class": "text",
      "id": "AAA26D08-49B1-4D5B-B01B-E290657D64E5"
    },
    {
      "class": "text",
      "id": "0032412F-1413-4B95-8451-972900CF30E9"
    },
    {
      "class": "text",
      "id": "0FE80406-8EC7-4DE4-9C20-75BD96940EE4"
    },
    {
      "class": "shapeGroup",
      "id": "002AB190-DF6C-46E1-BC2F-B9A512892C05"
    }
  ],
  "name": "Group 7 Copy 3",
  "nameIsFixed": false,
  "resizingConstraint": 63,
  "resizingType": 0,
  "rotation": 0,
  "shouldBreakMaskChain": false,
  "style": {
    "_class": "style",
    "endDecorationType": 0,
    "miterLimit": 10,
    "startDecorationType": 0
  }
}