{
  "_class": "group",
  "do_objectID": "9858A200-6293-448E-8102-E743A7229505",
  "exportOptions": {
    "_class": "exportOptions",
    "exportFormats": [
    ],
    "includedLayerIds": [
    ],
    "layerOptions": 0,
    "shouldTrim": false
  },
  "frame": {
    "_class": "rect",
    "constrainProportions": false,
    "height": 200,
    "width": 180,
    "x": 20,
    "y": 20
  },
  "hasClickThrough": false,
  "isFlippedHorizontal": false,
  "isFlippedVertical": false,
  "isLocked": false,
  "isVisible": true,
  "layerListExpandedType": 0,
  "layers": [
    {
      "class": "shapeGroup",
      "id": "0F083C44-B187-4301-B50C-608760AE7A8A"
    },
    {
      "class": "shapeGroup",
      "id": "98335B38-EF72-4951-BBDE-C305622A44EE"
    },
    {
      "class": "text",
      "id": "6DE811E4-2E1B-4DEF-8EA1-E0EE8D668B50"
    },
    {
      "class": "text",
      "id": "9F8E8BF3-51A3-4A9F-949B-ECDC036E16FF"
    },
    {
      "class": "text",
      "id": "73693004-C451-4ADF-9410-6E4FD1BC726E"
    }
  ],
  "name": "Swatch: #333333",
  "nameIsFixed": false,
  "resizingConstraint": 63,
  "resizingType": 0,
  "rotation": 0,
  "shouldBreakMaskChain": false,
  "style": {
    "_class": "style",
    "endDecorationType": 0,
    "miterLimit": 10,
    "startDecorationType": 0
  }
}