{
  "_class": "group",
  "do_objectID": "E7FE51FE-661E-4BE9-BE15-CBABFFB2ED41",
  "exportOptions": {
    "_class": "exportOptions",
    "do_objectID": "B55838E5-9B79-4E7E-879C-AFD1C5F5EED9",
    "exportFormats": [
    ],
    "includedLayerIds": [
    ],
    "layerOptions": 0,
    "shouldTrim": false
  },
  "frame": {
    "_class": "rect",
    "constrainProportions": false,
    "do_objectID": "6A86C1AD-8C7D-463D-A8AB-96C9E692D135",
    "height": 58,
    "width": 331,
    "x": 36,
    "y": 150
  },
  "hasClickThrough": false,
  "isFlippedHorizontal": false,
  "isFlippedVertical": false,
  "isLocked": false,
  "isVisible": true,
  "layerListExpandedType": 0,
  "layers": [
    {
      "class": "symbolInstance",
      "id": "30B92D1A-ECE9-4C75-9972-D7D419073D1C"
    },
    {
      "class": "text",
      "id": "0A2D277F-2D18-4D3F-A68D-6E25737E260B"
    }
  ],
  "name": "Group 13",
  "nameIsFixed": false,
  "resizingConstraint": 63,
  "resizingType": 0,
  "rotation": 0,
  "shouldBreakMaskChain": false,
  "style": {
    "_class": "style",
    "do_objectID": "5C97546B-5FC6-43AF-86D3-C9C8E433068D",
    "endDecorationType": 0,
    "miterLimit": 10,
    "startDecorationType": 0
  }
}