{
  "_class": "group",
  "do_objectID": "8A6B721A-C098-453D-BC42-308F5F6DC1B1",
  "exportOptions": {
    "_class": "exportOptions",
    "exportFormats": [
    ],
    "includedLayerIds": [
    ],
    "layerOptions": 0,
    "shouldTrim": false
  },
  "frame": {
    "_class": "rect",
    "constrainProportions": false,
    "height": 152,
    "width": 183,
    "x": 87,
    "y": 0
  },
  "hasClickThrough": false,
  "isFlippedHorizontal": false,
  "isFlippedVertical": false,
  "isLocked": false,
  "isVisible": true,
  "layerListExpandedType": 0,
  "layers": [
    {
      "class": "shapeGroup",
      "id": "BED246AB-553B-4159-A9DE-B2D6FBD33F14"
    },
    {
      "class": "text",
      "id": "E1B87717-64B4-4A7E-A46E-BE3E2E7C7FAC"
    },
    {
      "class": "shapeGroup",
      "id": "E2CBD08B-4795-4D1F-B7B7-F8F650E00BB5"
    },
    {
      "class": "shapeGroup",
      "id": "87C49871-5DC1-44EC-9F66-2FA25A6311F8"
    },
    {
      "class": "text",
      "id": "808D1723-F6B5-4A4E-9859-ED760ED97EDC"
    }
  ],
  "name": "Group 20",
  "nameIsFixed": false,
  "resizingConstraint": 63,
  "resizingType": 0,
  "rotation": 0,
  "shouldBreakMaskChain": false,
  "style": {
    "_class": "style",
    "endDecorationType": 0,
    "miterLimit": 10,
    "startDecorationType": 0
  }
}