{
  "_class": "group",
  "do_objectID": "ADB25041-4E53-4344-B9C0-2090411BACA8",
  "exportOptions": {
    "_class": "exportOptions",
    "exportFormats": [
    ],
    "includedLayerIds": [
    ],
    "layerOptions": 0,
    "shouldTrim": false
  },
  "frame": {
    "_class": "rect",
    "constrainProportions": false,
    "height": 64,
    "width": 1128,
    "x": -80,
    "y": -326
  },
  "hasClickThrough": false,
  "isFlippedHorizontal": false,
  "isFlippedVertical": false,
  "isLocked": false,
  "isVisible": true,
  "layerListExpandedType": 0,
  "layers": [
    {
      "class": "shapeGroup",
      "id": "7952B6B4-86BF-402E-A88E-A5FDBB9CFD2E"
    },
    {
      "class": "shapeGroup",
      "id": "CFF2DA99-C43C-4D7C-8D7C-7E4E89AE63AC"
    },
    {
      "class": "group",
      "id": "A0A21854-C173-4672-BF0D-A61B5EB9F467"
    }
  ],
  "name": "file/attachment/solid copy",
  "nameIsFixed": true,
  "resizingConstraint": 63,
  "resizingType": 0,
  "rotation": 0,
  "shouldBreakMaskChain": false,
  "style": {
    "_class": "style",
    "endDecorationType": 0,
    "miterLimit": 10,
    "startDecorationType": 0
  }
}