{
  "_class": "symbolInstance",
  "do_objectID": "83604A6B-5924-47AF-AD01-546A6E11501C",
  "exportOptions": {
    "_class": "exportOptions",
    "do_objectID": "3DCADF2D-3B3B-46C0-AE7B-CF48959DDC7F",
    "exportFormats": [
    ],
    "includedLayerIds": [
    ],
    "layerOptions": 0,
    "shouldTrim": false
  },
  "frame": {
    "_class": "rect",
    "constrainProportions": false,
    "do_objectID": "E7E1DD01-6FEA-40C0-BD0A-590A88084E51",
    "height": 24,
    "width": 24,
    "x": 8,
    "y": 8
  },
  "horizontalSpacing": 0,
  "isFlippedHorizontal": false,
  "isFlippedVertical": false,
  "isLocked": false,
  "isVisible": true,
  "layerListExpandedType": 0,
  "name": "icons / product / aws copy 5",
  "nameIsFixed": false,
  "overrideValues": [
  ],
  "overrides": {
  },
  "resizingConstraint": 63,
  "resizingType": 0,
  "rotation": 0,
  "scale": 1,
  "shouldBreakMaskChain": false,
  "style": {
    "_class": "style",
    "do_objectID": "54747F0D-0B68-4FC4-AEE0-461C9BD6A669",
    "endDecorationType": 0,
    "miterLimit": 10,
    "startDecorationType": 0
  },
  "symbolID": "5CF6EE68-C7A0-4840-938A-1841F3431466",
  "userInfo": {
    "com.animaapp.stc-sketch-plugin": {
      "kModelPropertiesKey": {
      }
    }
  },
  "verticalSpacing": 0
}