{
  "_class": "group",
  "do_objectID": "847AC59F-4D66-4AAB-BE2C-17EA0F34ADB9",
  "exportOptions": {
    "_class": "exportOptions",
    "exportFormats": [
    ],
    "includedLayerIds": [
    ],
    "layerOptions": 0,
    "shouldTrim": false
  },
  "frame": {
    "_class": "rect",
    "constrainProportions": false,
    "height": 312,
    "width": 905,
    "x": 240,
    "y": 1166
  },
  "hasClickThrough": false,
  "isFlippedHorizontal": false,
  "isFlippedVertical": false,
  "isLocked": false,
  "isVisible": true,
  "layerListExpandedType": 0,
  "layers": [
    {
      "class": "text",
      "id": "B558DA93-7303-44A1-9A9A-9F876575D628"
    },
    {
      "class": "shapeGroup",
      "id": "BE752217-4366-45F4-A5A0-97BE3E56AA30"
    },
    {
      "class": "text",
      "id": "396A2BB2-1116-431C-83D3-2FC8EF92F890"
    },
    {
      "class": "text",
      "id": "F90B0E79-90BD-41C5-B64F-D0C00AA5FFE3"
    },
    {
      "class": "shapeGroup",
      "id": "5DEA2259-4110-4726-B4A6-3A518464F2B3"
    },
    {
      "class": "shapeGroup",
      "id": "C5CC018E-8D1A-4485-BAA9-71D36D9D68B7"
    },
    {
      "class": "text",
      "id": "53C63050-16DD-4749-86F7-80D53C8ADDF0"
    },
    {
      "class": "text",
      "id": "06C7C278-7ABF-4772-AD4D-ED9AC9AE6F6A"
    },
    {
      "class": "text",
      "id": "3C47DA58-D710-4DB8-BC41-151763ADA0BF"
    },
    {
      "class": "text",
      "id": "6FD2D102-6D7F-4449-85D1-A4718D32A258"
    },
    {
      "class": "shapeGroup",
      "id": "1A38BB37-74F8-4114-ADC3-F10A53379D89"
    },
    {
      "class": "shapeGroup",
      "id": "4DE59496-E63D-4C18-9EFD-6EF740456103"
    }
  ],
  "name": "Storage Volumes",
  "nameIsFixed": true,
  "resizingConstraint": 63,
  "resizingType": 0,
  "rotation": 0,
  "shouldBreakMaskChain": false,
  "style": {
    "_class": "style",
    "endDecorationType": 0,
    "miterLimit": 10,
    "startDecorationType": 0
  }
}