{
  "_class": "group",
  "do_objectID": "97EE6EB3-1811-43AC-88A0-E23DE20E9917",
  "exportOptions": {
    "_class": "exportOptions",
    "exportFormats": [
    ],
    "includedLayerIds": [
    ],
    "layerOptions": 0,
    "shouldTrim": false
  },
  "frame": {
    "_class": "rect",
    "constrainProportions": false,
    "height": 150,
    "width": 212,
    "x": -4503,
    "y": 10915
  },
  "hasClickThrough": false,
  "isFlippedHorizontal": false,
  "isFlippedVertical": false,
  "isLocked": false,
  "isVisible": true,
  "layerListExpandedType": 0,
  "layers": [
    {
      "class": "symbolInstance",
      "id": "516A135F-D4DB-479D-A8F8-381F0C2AD4F3"
    },
    {
      "class": "text",
      "id": "47D8D201-9B7C-475C-B4BF-F1E201FB60ED"
    },
    {
      "class": "text",
      "id": "DB26C915-DDC4-47E8-9C86-899A8B019E37"
    },
    {
      "class": "shapeGroup",
      "id": "B573A6C3-C904-4725-AC59-59E5140D87EC"
    },
    {
      "class": "shapeGroup",
      "id": "4C5C4F8C-2323-4824-8431-552498E963B0"
    },
    {
      "class": "shapeGroup",
      "id": "58D99061-DF3A-45F3-B782-9D3505566C04"
    },
    {
      "class": "shapeGroup",
      "id": "A175E329-ED3B-4524-87DC-6E0D4F67CE8F"
    },
    {
      "class": "shapeGroup",
      "id": "C74C145C-0A20-4191-BEBA-37C0695BC5E3"
    },
    {
      "class": "shapeGroup",
      "id": "CDD62F32-ACF6-4B49-AB56-F5433D6500A6"
    },
    {
      "class": "shapeGroup",
      "id": "50B17E9D-F501-46AF-B82B-C52CF3C0D118"
    },
    {
      "class": "shapeGroup",
      "id": "77C8A3E0-D001-488B-B4C2-976F9ACE5AA7"
    },
    {
      "class": "shapeGroup",
      "id": "C5D38C37-3F05-49FC-B3C7-215425EFB0A1"
    },
    {
      "class": "shapeGroup",
      "id": "3BD52199-FFBF-4422-853D-A429DFDE87D5"
    },
    {
      "class": "shapeGroup",
      "id": "77D86154-0834-4B38-B386-B1F01E18B1C5"
    },
    {
      "class": "shapeGroup",
      "id": "E06C4328-D29D-4ED2-B1CF-B4D8806410A6"
    }
  ],
  "name": "Group 7",
  "nameIsFixed": false,
  "resizingConstraint": 63,
  "resizingType": 0,
  "rotation": 0,
  "shouldBreakMaskChain": false,
  "style": {
    "_class": "style",
    "endDecorationType": 0,
    "miterLimit": 10,
    "startDecorationType": 0
  }
}