{
  "_class": "group",
  "do_objectID": "06AA8AA4-D8D9-4CD3-82F0-C8A6BEB6CE5F",
  "exportOptions": {
    "_class": "exportOptions",
    "exportFormats": [
    ],
    "includedLayerIds": [
    ],
    "layerOptions": 0,
    "shouldTrim": false
  },
  "frame": {
    "_class": "rect",
    "constrainProportions": false,
    "height": 213,
    "width": 291,
    "x": 751,
    "y": 156
  },
  "hasClickThrough": false,
  "isFlippedHorizontal": false,
  "isFlippedVertical": false,
  "isLocked": false,
  "isVisible": true,
  "layerListExpandedType": 0,
  "layers": [
    {
      "class": "text",
      "id": "24A7B2A9-9F15-491D-A4E7-B9B274DAB02D"
    },
    {
      "class": "text",
      "id": "79EB79E7-9868-40F1-A6F9-E7D0EF90FDE2"
    },
    {
      "class": "text",
      "id": "34088323-84A8-4797-B5B4-E50A7AB1885C"
    },
    {
      "class": "text",
      "id": "B6350572-1E0F-403F-A8C3-FCFF6D97378F"
    },
    {
      "class": "text",
      "id": "2519FF0E-F5A0-4A35-A271-3083D6355C58"
    },
    {
      "class": "text",
      "id": "4AE672BD-03DE-49F7-945C-D0B39BFBD764"
    },
    {
      "class": "text",
      "id": "869CD3CF-CBEB-4399-95F8-30A56F5D7154"
    },
    {
      "class": "text",
      "id": "3294093A-C565-46D6-B0A6-DD8B306A9474"
    },
    {
      "class": "text",
      "id": "164D16B8-F7C2-47B6-B145-7E1338289E88"
    },
    {
      "class": "text",
      "id": "4913569F-B5DA-4EB2-B106-51FF6671BD5D"
    },
    {
      "class": "text",
      "id": "EEBBA871-CF24-4FB3-8891-82E5024F0502"
    },
    {
      "class": "text",
      "id": "85E7E54C-F259-48CE-A3FB-E94F0B4F99C9"
    },
    {
      "class": "text",
      "id": "A1AA6AEE-30A9-4AA7-9EC1-49276832AAD0"
    },
    {
      "class": "text",
      "id": "C1A4158B-EB07-4A64-A3E3-61340481E18D"
    },
    {
      "class": "text",
      "id": "39A63196-CFF5-4C30-9CFF-4A65520BC9DF"
    },
    {
      "class": "text",
      "id": "81CA9E8E-C516-4962-B3D9-C0DD235F5D00"
    }
  ],
  "name": "Group 16",
  "nameIsFixed": false,
  "resizingConstraint": 63,
  "resizingType": 0,
  "rotation": 0,
  "shouldBreakMaskChain": false,
  "style": {
    "_class": "style",
    "endDecorationType": 0,
    "miterLimit": 10,
    "startDecorationType": 0
  }
}