{
  "_class": "group",
  "do_objectID": "424DAFA9-84A4-4BB7-80AB-02232D3B8ED8",
  "exportOptions": {
    "_class": "exportOptions",
    "exportFormats": [
    ],
    "includedLayerIds": [
    ],
    "layerOptions": 0,
    "shouldTrim": false
  },
  "frame": {
    "_class": "rect",
    "constrainProportions": false,
    "height": 21,
    "width": 23,
    "x": 48,
    "y": 1394
  },
  "hasClickThrough": false,
  "isFlippedHorizontal": false,
  "isFlippedVertical": false,
  "isLocked": false,
  "isVisible": true,
  "layerListExpandedType": 0,
  "layers": [
    {
      "class": "shapeGroup",
      "id": "4558D9FD-BB74-4CD8-B610-EEE8A80FA2E9"
    },
    {
      "class": "shapeGroup",
      "id": "B5D1E267-967A-4379-A760-899812B8EB87"
    }
  ],
  "name": "Fill 775 + Fill 776",
  "nameIsFixed": false,
  "resizingConstraint": 63,
  "resizingType": 0,
  "rotation": 0,
  "shouldBreakMaskChain": false,
  "style": {
    "_class": "style",
    "endDecorationType": 0,
    "miterLimit": 10,
    "startDecorationType": 0
  }
}