{
  "_class": "group",
  "do_objectID": "69749C77-20F4-49C1-8D35-305DD905722C",
  "exportOptions": {
    "_class": "exportOptions",
    "exportFormats": [
    ],
    "includedLayerIds": [
    ],
    "layerOptions": 0,
    "shouldTrim": false
  },
  "frame": {
    "_class": "rect",
    "constrainProportions": false,
    "height": 129,
    "width": 48,
    "x": 1209,
    "y": 71
  },
  "hasClickThrough": false,
  "isFlippedHorizontal": false,
  "isFlippedVertical": false,
  "isLocked": false,
  "isVisible": true,
  "layerListExpandedType": 0,
  "layers": [
    {
      "class": "text",
      "id": "F8FB67DD-8846-42D2-A354-0397E2C66EAC"
    },
    {
      "class": "shapeGroup",
      "id": "1F07E8E7-980B-4837-BE3E-E1D95ED190A3"
    }
  ],
  "name": "Group 5 Copy",
  "nameIsFixed": false,
  "resizingConstraint": 63,
  "resizingType": 0,
  "rotation": 0,
  "shouldBreakMaskChain": false,
  "style": {
    "_class": "style",
    "endDecorationType": 0,
    "miterLimit": 10,
    "startDecorationType": 0
  }
}