{
  "_class": "bitmap",
  "clippingMask": "{{0, 0}, {1, 1}}",
  "do_objectID": "891198BD-3528-4EE0-9F5E-8B7575800A3A",
  "exportOptions": {
    "_class": "exportOptions",
    "do_objectID": "35D8E901-D98D-448B-9DE3-DFC463B6FBB5",
    "exportFormats": [
    ],
    "includedLayerIds": [
    ],
    "layerOptions": 0,
    "shouldTrim": false
  },
  "fillReplacesImage": false,
  "frame": {
    "_class": "rect",
    "constrainProportions": false,
    "do_objectID": "0DE92026-B65D-4643-A1B2-247D1F4CAB0A",
    "height": 202,
    "width": 126,
    "x": 227,
    "y": 827
  },
  "image": {
    "_class": "MSJSONFileReference",
    "_ref": "images/151cf0f12a9fba7a8cae93a377801f275c6eed20.png",
    "_ref_class": "MSImageData"
  },
  "intendedDPI": 0,
  "isFlippedHorizontal": false,
  "isFlippedVertical": false,
  "isLocked": false,
  "isVisible": true,
  "layerListExpandedType": 0,
  "name": "Bitmap",
  "nameIsFixed": false,
  "resizingConstraint": 63,
  "resizingType": 0,
  "rotation": 90,
  "shouldBreakMaskChain": false,
  "style": {
    "_class": "style",
    "do_objectID": "A87E7EDF-657B-463A-84D8-08BB371E4D0E",
    "endDecorationType": 0,
    "miterLimit": 10,
    "startDecorationType": 0
  }
}