{
  "_class": "symbolInstance",
  "do_objectID": "0D989233-EA23-4760-91EF-27565633DAB5",
  "exportOptions": {
    "_class": "exportOptions",
    "do_objectID": "FEE29A63-2492-4575-9EE2-18B4B9BDD3D1",
    "exportFormats": [
    ],
    "includedLayerIds": [
    ],
    "layerOptions": 0,
    "shouldTrim": false
  },
  "frame": {
    "_class": "rect",
    "constrainProportions": false,
    "do_objectID": "A3017555-73B1-4921-A758-28FC65653ED6",
    "height": 17,
    "width": 17,
    "x": 16,
    "y": 621
  },
  "horizontalSpacing": 0,
  "isFlippedHorizontal": false,
  "isFlippedVertical": false,
  "isLocked": false,
  "isVisible": true,
  "layerListExpandedType": 0,
  "name": "Checkbox/Unchecked Copy 6",
  "nameIsFixed": false,
  "originalObjectID": "A9BDBFD0-784E-4B29-A5FC-D8AE49A78EB1",
  "overrideValues": [
  ],
  "overrides": {
  },
  "resizingConstraint": 0,
  "resizingType": 0,
  "rotation": 0,
  "scale": 1,
  "shouldBreakMaskChain": false,
  "style": {
    "_class": "style",
    "do_objectID": "F621B713-67BC-40AA-A59B-12F84B358EA8",
    "endDecorationType": 0,
    "miterLimit": 10,
    "startDecorationType": 0
  },
  "symbolID": "F29741DB-DADF-4BA0-B508-E0E33966F66B",
  "userInfo": {
    "com.invisionlabs.library": {
      "original-layer": {
        "originalID": "8438F46D-D545-4306-A9E9-9BC05BEB587C",
        "version": 2
      }
    }
  },
  "verticalSpacing": 0
}