{
  "_class": "group",
  "do_objectID": "F63D2259-D1F4-4BA1-A373-135C6D9A6BB2",
  "exportOptions": {
    "_class": "exportOptions",
    "exportFormats": [
    ],
    "includedLayerIds": [
    ],
    "layerOptions": 0,
    "shouldTrim": false
  },
  "frame": {
    "_class": "rect",
    "constrainProportions": false,
    "height": 24,
    "width": 462,
    "x": 20,
    "y": 8
  },
  "hasClickThrough": false,
  "isFlippedHorizontal": false,
  "isFlippedVertical": false,
  "isLocked": false,
  "isVisible": true,
  "layerListExpandedType": 0,
  "layers": [
    {
      "class": "text",
      "id": "E1BAAB1A-A755-482C-9988-A7943584C42B"
    },
    {
      "class": "text",
      "id": "1150BB2E-6B49-4DC6-A723-5347D6CF0048"
    },
    {
      "class": "text",
      "id": "27902CA7-DEFB-474A-B397-CA07966332A7"
    }
  ],
  "name": "footer:text",
  "nameIsFixed": true,
  "resizingConstraint": 63,
  "resizingType": 0,
  "rotation": 0,
  "shouldBreakMaskChain": false,
  "style": {
    "_class": "style",
    "endDecorationType": 0,
    "miterLimit": 10,
    "startDecorationType": 0
  }
}