{
  "_class": "shapePath",
  "booleanOperation": -1,
  "do_objectID": "713258FC-608E-4191-A6D2-3B8112F9832C",
  "edited": true,
  "exportOptions": {
    "_class": "exportOptions",
    "exportFormats": [
    ],
    "includedLayerIds": [
    ],
    "layerOptions": 0,
    "shouldTrim": false
  },
  "frame": {
    "_class": "rect",
    "constrainProportions": false,
    "height": 7.850005548801082,
    "width": 7.848732850106396,
    "x": 1.90840406031586,
    "y": 18.24031769218826
  },
  "isClosed": true,
  "isFlippedHorizontal": false,
  "isFlippedVertical": false,
  "isLocked": false,
  "isVisible": true,
  "layerListExpandedType": 0,
  "name": "Path",
  "nameIsFixed": false,
  "pointRadiusBehaviour": 1,
  "points": [
    {
      "_class": "curvePoint",
      "cornerRadius": 0,
      "curveFrom": "{0.22375141884222469, 1}",
      "curveMode": 2,
      "curveTo": "{0.77609048159558947, 1}",
      "hasCurveFrom": true,
      "hasCurveTo": true,
      "point": "{0.49991892330144305, 1}"
    },
    {
      "_class": "curvePoint",
      "cornerRadius": 0,
      "curveFrom": "{0, 0.22387321660181589}",
      "curveMode": 2,
      "curveTo": "{0, 0.77612678339818386}",
      "hasCurveFrom": true,
      "hasCurveTo": true,
      "point": "{0, 0.50000000000000011}"
    },
    {
      "_class": "curvePoint",
      "cornerRadius": 0,
      "curveFrom": "{0.77608642776066161, 0}",
      "curveMode": 2,
      "curveTo": "{0.22375141884222469, 0}",
      "hasCurveFrom": true,
      "hasCurveTo": true,
      "point": "{0.49991892330144305, 0}"
    },
    {
      "_class": "curvePoint",
      "cornerRadius": 0,
      "curveFrom": "{1, 0.77612678339818386}",
      "curveMode": 2,
      "curveTo": "{1, 0.22387321660181589}",
      "hasCurveFrom": true,
      "hasCurveTo": true,
      "point": "{1, 0.50000000000000011}"
    }
  ],
  "resizingConstraint": 63,
  "resizingType": 0,
  "rotation": 0,
  "shouldBreakMaskChain": false
}