{
  "_class": "group",
  "do_objectID": "525914B8-5B66-4501-A75D-FBB8608C5D77",
  "exportOptions": {
    "_class": "exportOptions",
    "exportFormats": [
    ],
    "includedLayerIds": [
    ],
    "layerOptions": 0,
    "shouldTrim": false
  },
  "frame": {
    "_class": "rect",
    "constrainProportions": false,
    "height": 80,
    "width": 8,
    "x": 15,
    "y": 43
  },
  "hasClickThrough": false,
  "isFlippedHorizontal": false,
  "isFlippedVertical": false,
  "isLocked": false,
  "isVisible": true,
  "layerListExpandedType": 0,
  "layers": [
    {
      "class": "shapeGroup",
      "id": "2D3E110F-AD90-40B2-8B3D-383188516F73"
    },
    {
      "class": "text",
      "id": "FD522980-C67B-4E4A-AA4C-3D96F3BD2803"
    }
  ],
  "name": "Group 6",
  "nameIsFixed": false,
  "resizingConstraint": 63,
  "resizingType": 0,
  "rotation": 0,
  "shouldBreakMaskChain": false,
  "style": {
    "_class": "style",
    "endDecorationType": 0,
    "miterLimit": 10,
    "startDecorationType": 0
  }
}