{
  "_class": "group",
  "do_objectID": "82C6083F-1B65-4BEC-95D9-30EDB8A934A5",
  "exportOptions": {
    "_class": "exportOptions",
    "exportFormats": [
    ],
    "includedLayerIds": [
    ],
    "layerOptions": 0,
    "shouldTrim": false
  },
  "frame": {
    "_class": "rect",
    "constrainProportions": false,
    "height": 30,
    "width": 124,
    "x": 1,
    "y": 29
  },
  "hasClickThrough": false,
  "isFlippedHorizontal": false,
  "isFlippedVertical": false,
  "isLocked": false,
  "isVisible": true,
  "layerListExpandedType": 2,
  "layers": [
    {
      "class": "shapeGroup",
      "id": "3CCD534E-BC17-459E-B2C5-AEDBA7112C3F"
    },
    {
      "class": "shapeGroup",
      "id": "43D747C4-D366-4D2E-AB18-C5B1D8BC2D3D"
    },
    {
      "class": "text",
      "id": "11924E55-DA6F-48FA-A0D4-50CB393E4609"
    }
  ],
  "name": "Time box Copy",
  "nameIsFixed": true,
  "resizingConstraint": 63,
  "resizingType": 0,
  "rotation": 0,
  "shouldBreakMaskChain": false,
  "style": {
    "_class": "style",
    "endDecorationType": 0,
    "miterLimit": 10,
    "startDecorationType": 0
  }
}