{
  "_class": "group",
  "do_objectID": "A22FBB7E-B061-4ABA-8B23-A296FD17636B",
  "exportOptions": {
    "_class": "exportOptions",
    "exportFormats": [
    ],
    "includedLayerIds": [
    ],
    "layerOptions": 0,
    "shouldTrim": false
  },
  "frame": {
    "_class": "rect",
    "constrainProportions": false,
    "height": 364,
    "width": 552,
    "x": 396,
    "y": 82
  },
  "hasClickThrough": false,
  "isFlippedHorizontal": false,
  "isFlippedVertical": false,
  "isLocked": false,
  "isVisible": true,
  "layerListExpandedType": 0,
  "layers": [
    {
      "class": "shapeGroup",
      "id": "BF87A64B-2E8C-4004-B17D-0D98BC9E63E1"
    },
    {
      "class": "shapeGroup",
      "id": "45FCC7C1-23BE-40AA-B02E-92541E4CC96C"
    },
    {
      "class": "shapeGroup",
      "id": "99219BB5-1268-427D-8646-096A9F9C08F1"
    },
    {
      "class": "shapeGroup",
      "id": "4379ED99-C9BC-41D1-9B57-8EE33829DA15"
    },
    {
      "class": "symbolInstance",
      "id": "42696EDC-EA6C-4497-8FD5-CD5066E9C963"
    },
    {
      "class": "shapeGroup",
      "id": "D908424C-0EF2-4AF1-9940-F8A25C7CC9E0"
    },
    {
      "class": "text",
      "id": "BC9A1C42-365D-42B5-8F74-6D2156F60B9D"
    },
    {
      "class": "text",
      "id": "6831652B-F171-4E1C-825B-F26B2EA9A832"
    },
    {
      "class": "text",
      "id": "1DAAFB0D-9A56-4FCE-84B6-9C699C94A48F"
    },
    {
      "class": "text",
      "id": "B174AC7C-D4E6-438D-B769-491624C940A3"
    }
  ],
  "name": "Group",
  "nameIsFixed": false,
  "resizingConstraint": 63,
  "resizingType": 0,
  "rotation": 0,
  "shouldBreakMaskChain": false,
  "style": {
    "_class": "style",
    "endDecorationType": 0,
    "miterLimit": 10,
    "startDecorationType": 0
  }
}