{
  "_class": "shapeGroup",
  "clippingMaskMode": 0,
  "do_objectID": "2705C1C3-AC83-47E0-A2CC-82A0E838BCC3",
  "exportOptions": {
    "_class": "exportOptions",
    "do_objectID": "469EB2F6-6B63-4DEB-9159-59A296FF53F3",
    "exportFormats": [
    ],
    "includedLayerIds": [
    ],
    "layerOptions": 0,
    "shouldTrim": false
  },
  "frame": {
    "_class": "rect",
    "constrainProportions": true,
    "do_objectID": "37A20D94-7AA0-43EF-AF73-23BFB9BDEE8A",
    "height": 6.3,
    "width": 6.3,
    "x": 0.2624236400515656,
    "y": 0.4260909493459621
  },
  "hasClickThrough": false,
  "hasClippingMask": false,
  "isFlippedHorizontal": false,
  "isFlippedVertical": false,
  "isLocked": false,
  "isVisible": true,
  "layerListExpandedType": 0,
  "layers": [
    {
      "class": "shapePath",
      "id": "DA4BE322-2B1F-40A3-8721-9C913C8F123A"
    }
  ],
  "name": "redline-end",
  "nameIsFixed": true,
  "originalObjectID": "8FE506EC-E785-42C7-9E66-EECBE7C29DC1",
  "resizingConstraint": 45,
  "resizingType": 1,
  "rotation": 0,
  "shouldBreakMaskChain": false,
  "style": {
    "_class": "style",
    "blur": {
      "_class": "blur",
      "center": "{0.5, 0.5}",
      "do_objectID": "A44C5274-6ECE-44B0-8A01-095C5B9A5DBA",
      "isEnabled": false,
      "motionAngle": 0,
      "radius": 9,
      "type": 0
    },
    "borders": [
      {
        "_class": "border",
        "color": {
          "_class": "color",
          "alpha": 1,
          "blue": 0.4784313725490194,
          "green": 0.2509803921568627,
          "red": 0.9254901960784314
        },
        "fillType": 0,
        "isEnabled": true,
        "position": 1,
        "thickness": 0.9
      }
    ],
    "do_objectID": "D040D491-E3BF-4128-B628-AA92AEB68B33",
    "endDecorationType": 0,
    "fills": [
      {
        "_class": "fill",
        "color": {
          "_class": "color",
          "alpha": 1,
          "blue": 1,
          "green": 1,
          "red": 1
        },
        "fillType": 0,
        "isEnabled": true,
        "noiseIndex": 0,
        "noiseIntensity": 0,
        "patternFillType": 0,
        "patternTileScale": 1
      }
    ],
    "miterLimit": 10,
    "startDecorationType": 0
  },
  "windingRule": 1
}