{
  "_class": "group",
  "do_objectID": "E68F14F8-7BA3-4B78-A31A-5D77196B352F",
  "exportOptions": {
    "_class": "exportOptions",
    "exportFormats": [
    ],
    "includedLayerIds": [
    ],
    "layerOptions": 0,
    "shouldTrim": false
  },
  "frame": {
    "_class": "rect",
    "constrainProportions": false,
    "height": 582,
    "width": 1024,
    "x": 70707,
    "y": 14781
  },
  "hasClickThrough": false,
  "isFlippedHorizontal": false,
  "isFlippedVertical": false,
  "isLocked": false,
  "isVisible": true,
  "layerListExpandedType": 0,
  "layers": [
    {
      "class": "symbolInstance",
      "id": "3157E60B-D2E8-4876-92EB-C3CCA5A48C20"
    },
    {
      "class": "symbolInstance",
      "id": "8D756A97-E280-4437-B3A4-387F010B014D"
    },
    {
      "class": "group",
      "id": "1A4A2B3F-B239-4C25-AA57-562847158153"
    },
    {
      "class": "text",
      "id": "40363C7E-955D-41F3-AB34-991C5B80F94F"
    },
    {
      "class": "text",
      "id": "804AE273-9498-488E-9C8F-E34FA06CE7C7"
    },
    {
      "class": "text",
      "id": "00BD8205-6295-465E-9D23-A4A42FE37399"
    }
  ],
  "name": "State-Loading",
  "nameIsFixed": true,
  "resizingConstraint": 63,
  "resizingType": 0,
  "rotation": 0,
  "shouldBreakMaskChain": false,
  "style": {
    "_class": "style",
    "endDecorationType": 0,
    "miterLimit": 10,
    "startDecorationType": 0
  }
}